loadyamlauto
