Metadata-Version: 1.0
Name: loadyamlauto
Version: 0.0.4
Summary: 自动加载yaml
Home-page: http://172.16.1.41:10080/aip/face-db.git
Author: yuanpeng
Author-email: 862877214@qq.com
License: UNKNOWN
Platform: UNKNOWN
